gwisp
