Metadata-Version: 1.1
Name: gwisp
Version: 0.3.0
Summary: http programing interface of tracker storage
Home-page: https://github.com/kevin-leptons/gwisp
Author: kevin leptons
Author-email: kevin.leptons@gmail.com
License: UNKNOWN
Download-URL: https://github.com/kevin-leptons/gwisp
Keywords: time tracker storage api
Platform: UNKNOWN
